README.md
setup.py
ym.py
ym.egg-info/PKG-INFO
ym.egg-info/SOURCES.txt
ym.egg-info/dependency_links.txt
ym.egg-info/top_level.txt