Metadata-Version: 2.1
Name: ym
Version: 1.0.2
Summary: Data type that handles year and month values.
Home-page: https://github.com/hoto17296/python-ym
Author: hoto17296
License: MIT
Platform: UNKNOWN
